{
  "timestamp": "20260131_203442",
  "experiment": "echo_sweep",
  "version": "7.1",
  "test_case": {
    "val_a": 0,
    "val_b": 0
  },
  "results": [
    {
      "mode": "BASELINE",
      "syndrome": 0.04150390625,
      "delta": 0.0,
      "counts": {
        "000": 3905,
        "001": 52,
        "010": 49,
        "111": 14,
        "100": 55,
        "110": 13,
        "011": 4,
        "101": 4
      }
    },
    {
      "mode": "HAHN_D0",
      "desc": "Hahn Echo (Minimal)",
      "syndrome": 0.051513671875,
      "delta": 0.010009765625,
      "counts": {
        "000": 3864,
        "011": 3,
        "101": 9,
        "010": 58,
        "001": 80,
        "100": 60,
        "111": 13,
        "110": 9
      }
    },
    {
      "mode": "HAHN_D5",
      "desc": "Hahn Echo (Delay=5)",
      "syndrome": 0.043701171875,
      "delta": 0.002197265625,
      "counts": {
        "000": 3906,
        "010": 50,
        "001": 69,
        "100": 58,
        "110": 8,
        "101": 3,
        "111": 2
      }
    },
    {
      "mode": "CPMG_D0",
      "desc": "CPMG-2 (Minimal)",
      "syndrome": 0.047119140625,
      "delta": 0.005615234375,
      "counts": {
        "000": 3881,
        "100": 62,
        "111": 14,
        "010": 52,
        "001": 65,
        "101": 5,
        "110": 16,
        "011": 1
      }
    },
    {
      "mode": "CPMG_D5",
      "desc": "CPMG-2 (Delay=5)",
      "syndrome": 0.05908203125,
      "delta": 0.017578125,
      "counts": {
        "000": 3837,
        "110": 7,
        "101": 7,
        "100": 92,
        "001": 78,
        "010": 59,
        "111": 13,
        "011": 3
      }
    }
  ],
  "best_config": "BASELINE",
  "best_syndrome": 0.04150390625,
  "baseline_syndrome": 0.04150390625
}